bqrepl/__init__.py
bqrepl/__main__.py
bqrepl/completer.py
bqrepl/config.py
bqrepl/lexer.py
bqrepl/main.py
bqrepl-0.2.4.dist-info/LICENSE
bqrepl-0.2.4.dist-info/METADATA
bqrepl-0.2.4.dist-info/WHEEL
bqrepl-0.2.4.dist-info/entry_points.txt
bqrepl-0.2.4.dist-info/top_level.txt
bqrepl-0.2.4.dist-info/RECORD
