Metadata-Version: 2.1
Name: bqrepl
Version: 0.2.4
Summary: REPL for Big Query
Home-page: https://github.com/bartekpi/bqrepl
Author: Bartosz Pieniak
Author-email: bartosz.pieniak@gmail.com
License: MIT
Platform: UNKNOWN
Classifier: License :: OSI Approved :: MIT License
Classifier: Intended Audience :: Developers
Classifier: Programming Language :: Python
Classifier: Programming Language :: Python :: 3
Classifier: Programming Language :: Python :: 3.6
Classifier: Programming Language :: Python :: 3.7
Classifier: Programming Language :: Python :: 3.8
Classifier: Programming Language :: Python :: 3.9
Classifier: Programming Language :: SQL
Classifier: Topic :: Database
Classifier: Topic :: Database :: Front-Ends
Requires-Python: >=3.6
License-File: LICENSE
Requires-Dist: click (>=8.0.1)
Requires-Dist: prompt-toolkit (>=3.0.18)
Requires-Dist: pytz (>=2021.1)
Requires-Dist: logzero (>=1.7.0)
Requires-Dist: google-cloud-bigquery (>=2.18.0)
Requires-Dist: Pygments (>=2.9.0)
Requires-Dist: pydata-google-auth (>=1.2.0)
Requires-Dist: requests (>=2.25.1)
